{
  "project_info": {
    "project_number": "505909453899",
    "firebase_url": "https://realtime-chat-554f9.firebaseio.com",
    "project_id": "realtime-chat-554f9",
    "storage_bucket": "realtime-chat-554f9.appspot.com"
  },
  "client": [
    {
      "client_info": {
        "mobilesdk_app_id": "1:505909453899:android:68823547eb7f096e3499ce",
        "android_client_info": {
          "package_name": "com.lescigognes.chatentempsreel"
        }
      },
      "oauth_client": [
        {
          "client_id": "505909453899-a2p6a0bqsnek3bg0qolphq4b7feo9qa9.apps.googleusercontent.com",
          "client_type": 3
        }
      ],
      "api_key": [
        {
          "current_key": "AIzaSyDevgfnWjD5-WdF1ZA_sZvV0hwqSJ18Y1M"
        }
      ],
      "services": {
        "appinvite_service": {
          "other_platform_oauth_client": [
            {
              "client_id": "505909453899-a2p6a0bqsnek3bg0qolphq4b7feo9qa9.apps.googleusercontent.com",
              "client_type": 3
            }
          ]
        }
      }
    }
  ],
  "configuration_version": "1"
}